alphausblue/__init__.py
alphausblue/admin/__init__.py
alphausblue/admin/v1/__init__.py
alphausblue/admin/v1/admin_pb2.py
alphausblue/admin/v1/admin_pb2_grpc.py
alphausblue/api/__init__.py
alphausblue/api/account_pb2.py
alphausblue/api/accountgroup_pb2.py
alphausblue/api/apiclient_pb2.py
alphausblue/api/budget_pb2.py
alphausblue/api/coverage_pb2.py
alphausblue/api/forecast_pb2.py
alphausblue/api/grouprootuser_pb2.py
alphausblue/api/keyvalue_pb2.py
alphausblue/api/operation_pb2.py
alphausblue/api/rbac_pb2.py
alphausblue/api/user_pb2.py
alphausblue/api/utilization_pb2.py
alphausblue/api/aws/__init__.py
alphausblue/api/aws/calculator_pb2.py
alphausblue/api/aws/cost_pb2.py
alphausblue/api/aws/recommendation_pb2.py
alphausblue/api/aws/reduction_pb2.py
alphausblue/api/ripple/__init__.py
alphausblue/api/ripple/org_pb2.py
alphausblue/api/ripple/payer_pb2.py
alphausblue/api/ripple/reseller_pb2.py
alphausblue/billing/__init__.py
alphausblue/billing/v1/__init__.py
alphausblue/billing/v1/billing_pb2.py
alphausblue/billing/v1/billing_pb2_grpc.py
alphausblue/connection/__init__.py
alphausblue/connection/conn.py
alphausblue/connection/header_interceptor.py
alphausblue/connection/interceptor.py
alphausblue/connection/session.py
alphausblue/cost/__init__.py
alphausblue/cost/v1/__init__.py
alphausblue/cost/v1/cost_pb2.py
alphausblue/cost/v1/cost_pb2_grpc.py
alphausblue/examples/__init__.py
alphausblue/examples/cost.py
alphausblue/examples/iam.py
alphausblue/examples/org.py
alphausblue/iam/__init__.py
alphausblue/iam/v1/__init__.py
alphausblue/iam/v1/iam_pb2.py
alphausblue/iam/v1/iam_pb2_grpc.py
alphausblue/kvstore/__init__.py
alphausblue/kvstore/v1/__init__.py
alphausblue/kvstore/v1/kvstore_pb2.py
alphausblue/kvstore/v1/kvstore_pb2_grpc.py
alphausblue/operations/__init__.py
alphausblue/operations/v1/__init__.py
alphausblue/operations/v1/operations_pb2.py
alphausblue/operations/v1/operations_pb2_grpc.py
alphausblue/org/__init__.py
alphausblue/org/v1/__init__.py
alphausblue-1.1.4.dist-info/LICENSE
alphausblue-1.1.4.dist-info/METADATA
alphausblue-1.1.4.dist-info/WHEEL
alphausblue-1.1.4.dist-info/top_level.txt
alphausblue-1.1.4.dist-info/RECORD
